unleash_django/__init__.py
unleash_django/constants.py
unleash_django/exceptions.py
unleash_django/models.py
unleash_django/validators.py
unleash_django/api/__init__.py
unleash_django/api/method.py
unleash_django/client/__init__.py
unleash_django/client/client.py
unleash_django/decorators/__init__.py
unleash_django/decorators/method_flag.py
unleash_django/decorators/view_flag.py
unleash_django_util-0.4.3.dist-info/LICENSE
unleash_django_util-0.4.3.dist-info/METADATA
unleash_django_util-0.4.3.dist-info/WHEEL
unleash_django_util-0.4.3.dist-info/top_level.txt
unleash_django_util-0.4.3.dist-info/RECORD
