Metadata-Version: 2.1
Name: unleash-django-util
Version: 0.4.3
Summary: Unleash Django utility package
Home-page: https://github.com/miare-ir/unleash-django
Author: Amir Alaghmandan
Author-email: amir.amotlagh@gmail.com
License: UNKNOWN
Platform: UNKNOWN
Classifier: License :: OSI Approved :: MIT License
Classifier: Programming Language :: Python
Classifier: Programming Language :: Python :: 3.5
Classifier: Programming Language :: Python :: 3.6
Classifier: Programming Language :: Python :: 3.7
Classifier: Programming Language :: Python :: 3.8
Classifier: Programming Language :: Python :: 3.9
Classifier: Programming Language :: Python :: 3.10
Classifier: Framework :: Django
Classifier: Framework :: Django :: 2.2
Classifier: Framework :: Django :: 3.0
Classifier: Framework :: Django :: 3.1
Classifier: Framework :: Django :: 3.2
License-File: LICENSE
Requires-Dist: python-dateutil (>=2.8.2)
Requires-Dist: UnleashClient (>=5.2.0)
Requires-Dist: Django (>=2.2)
